[
  {
    "sku_id": "SELLER_C-001",
    "seller_id": "seller_c",
    "seller_name": "Yiwu Brightline Trading",
    "product_line": "TWS Earbuds AeroBuds X2",
    "variant": "Black",
    "unit_price_usd": 9.51,
    "moq": 100,
    "stock_qty": 45,
    "lead_time_days": 12
  },
  {
    "sku_id": "SELLER_C-002",
    "seller_id": "seller_c",
    "seller_name": "Yiwu Brightline Trading",
    "product_line": "TWS Earbuds AeroBuds X2",
    "variant": "White",
    "unit_price_usd": 8.64,
    "moq": 200,
    "stock_qty": 1200,
    "lead_time_days": 15
  },
  {
    "sku_id": "SELLER_C-003",
    "seller_id": "seller_c",
    "seller_name": "Yiwu Brightline Trading",
    "product_line": "TWS Earbuds AeroBuds X2",
    "variant": "Navy Blue",
    "unit_price_usd": 10.66,
    "moq": 50,
    "stock_qty": 120,
    "lead_time_days": 10
  },
  {
    "sku_id": "SELLER_C-004",
    "seller_id": "seller_c",
    "seller_name": "Yiwu Brightline Trading",
    "product_line": "TWS Earbuds AeroBuds X2",
    "variant": "Rose Gold",
    "unit_price_usd": 10.58,
    "moq": 100,
    "stock_qty": 1200,
    "lead_time_days": 10
  },
  {
    "sku_id": "SELLER_C-005",
    "seller_id": "seller_c",
    "seller_name": "Yiwu Brightline Trading",
    "product_line": "TWS Earbuds AeroBuds X2",
    "variant": "Graphite",
    "unit_price_usd": 9.99,
    "moq": 50,
    "stock_qty": 560,
    "lead_time_days": 12
  },
  {
    "sku_id": "SELLER_C-006",
    "seller_id": "seller_c",
    "seller_name": "Yiwu Brightline Trading",
    "product_line": "Over-Ear Headphones SoundMax H7",
    "variant": "Black",
    "unit_price_usd": 16.83,
    "moq": 50,
    "stock_qty": 560,
    "lead_time_days": 10
  },
  {
    "sku_id": "SELLER_C-007",
    "seller_id": "seller_c",
    "seller_name": "Yiwu Brightline Trading",
    "product_line": "Over-Ear Headphones SoundMax H7",
    "variant": "Silver",
    "unit_price_usd": 15.43,
    "moq": 50,
    "stock_qty": 560,
    "lead_time_days": 15
  },
  {
    "sku_id": "SELLER_C-008",
    "seller_id": "seller_c",
    "seller_name": "Yiwu Brightline Trading",
    "product_line": "Over-Ear Headphones SoundMax H7",
    "variant": "Midnight Blue",
    "unit_price_usd": 17.31,
    "moq": 100,
    "stock_qty": 340,
    "lead_time_days": 10
  },
  {
    "sku_id": "SELLER_C-009",
    "seller_id": "seller_c",
    "seller_name": "Yiwu Brightline Trading",
    "product_line": "Over-Ear Headphones SoundMax H7",
    "variant": "Beige",
    "unit_price_usd": 17.33,
    "moq": 100,
    "stock_qty": 80,
    "lead_time_days": 7
  },
  {
    "sku_id": "SELLER_C-010",
    "seller_id": "seller_c",
    "seller_name": "Yiwu Brightline Trading",
    "product_line": "Over-Ear Headphones SoundMax H7",
    "variant": "Red",
    "unit_price_usd": 12.2,
    "moq": 100,
    "stock_qty": 900,
    "lead_time_days": 15
  },
  {
    "sku_id": "SELLER_C-011",
    "seller_id": "seller_c",
    "seller_name": "Yiwu Brightline Trading",
    "product_line": "Bluetooth Speaker BoomCube Mini",
    "variant": "Black",
    "unit_price_usd": 12.71,
    "moq": 100,
    "stock_qty": 560,
    "lead_time_days": 10
  },
  {
    "sku_id": "SELLER_C-012",
    "seller_id": "seller_c",
    "seller_name": "Yiwu Brightline Trading",
    "product_line": "Bluetooth Speaker BoomCube Mini",
    "variant": "Teal",
    "unit_price_usd": 12.63,
    "moq": 50,
    "stock_qty": 80,
    "lead_time_days": 7
  },
  {
    "sku_id": "SELLER_C-013",
    "seller_id": "seller_c",
    "seller_name": "Yiwu Brightline Trading",
    "product_line": "Bluetooth Speaker BoomCube Mini",
    "variant": "Orange",
    "unit_price_usd": 13.02,
    "moq": 100,
    "stock_qty": 340,
    "lead_time_days": 15
  },
  {
    "sku_id": "SELLER_C-014",
    "seller_id": "seller_c",
    "seller_name": "Yiwu Brightline Trading",
    "product_line": "Bluetooth Speaker BoomCube Mini",
    "variant": "White",
    "unit_price_usd": 10.21,
    "moq": 100,
    "stock_qty": 340,
    "lead_time_days": 7
  },
  {
    "sku_id": "SELLER_C-015",
    "seller_id": "seller_c",
    "seller_name": "Yiwu Brightline Trading",
    "product_line": "Bluetooth Speaker BoomCube Mini",
    "variant": "Camo",
    "unit_price_usd": 11.92,
    "moq": 200,
    "stock_qty": 560,
    "lead_time_days": 12
  },
  {
    "sku_id": "SELLER_C-016",
    "seller_id": "seller_c",
    "seller_name": "Yiwu Brightline Trading",
    "product_line": "GaN Wall Charger PowerNode 65W",
    "variant": "US Plug",
    "unit_price_usd": 9.56,
    "moq": 100,
    "stock_qty": 560,
    "lead_time_days": 15
  },
  {
    "sku_id": "SELLER_C-017",
    "seller_id": "seller_c",
    "seller_name": "Yiwu Brightline Trading",
    "product_line": "GaN Wall Charger PowerNode 65W",
    "variant": "EU Plug",
    "unit_price_usd": 8.79,
    "moq": 300,
    "stock_qty": 560,
    "lead_time_days": 7
  },
  {
    "sku_id": "SELLER_C-018",
    "seller_id": "seller_c",
    "seller_name": "Yiwu Brightline Trading",
    "product_line": "GaN Wall Charger PowerNode 65W",
    "variant": "UK Plug",
    "unit_price_usd": 6.46,
    "moq": 100,
    "stock_qty": 340,
    "lead_time_days": 12
  },
  {
    "sku_id": "SELLER_C-019",
    "seller_id": "seller_c",
    "seller_name": "Yiwu Brightline Trading",
    "product_line": "GaN Wall Charger PowerNode 65W",
    "variant": "AU Plug",
    "unit_price_usd": 6.14,
    "moq": 300,
    "stock_qty": 80,
    "lead_time_days": 12
  },
  {
    "sku_id": "SELLER_C-020",
    "seller_id": "seller_c",
    "seller_name": "Yiwu Brightline Trading",
    "product_line": "GaN Wall Charger PowerNode 65W",
    "variant": "Universal",
    "unit_price_usd": 9.0,
    "moq": 100,
    "stock_qty": 80,
    "lead_time_days": 7
  },
  {
    "sku_id": "SELLER_C-021",
    "seller_id": "seller_c",
    "seller_name": "Yiwu Brightline Trading",
    "product_line": "Power Bank VoltCell 20000mAh",
    "variant": "Black",
    "unit_price_usd": 12.6,
    "moq": 300,
    "stock_qty": 340,
    "lead_time_days": 12
  },
  {
    "sku_id": "SELLER_C-022",
    "seller_id": "seller_c",
    "seller_name": "Yiwu Brightline Trading",
    "product_line": "Power Bank VoltCell 20000mAh",
    "variant": "White",
    "unit_price_usd": 10.41,
    "moq": 200,
    "stock_qty": 120,
    "lead_time_days": 10
  },
  {
    "sku_id": "SELLER_C-023",
    "seller_id": "seller_c",
    "seller_name": "Yiwu Brightline Trading",
    "product_line": "Power Bank VoltCell 20000mAh",
    "variant": "Slate Grey",
    "unit_price_usd": 12.47,
    "moq": 50,
    "stock_qty": 45,
    "lead_time_days": 12
  },
  {
    "sku_id": "SELLER_C-024",
    "seller_id": "seller_c",
    "seller_name": "Yiwu Brightline Trading",
    "product_line": "Power Bank VoltCell 20000mAh",
    "variant": "Blue",
    "unit_price_usd": 14.13,
    "moq": 50,
    "stock_qty": 45,
    "lead_time_days": 12
  },
  {
    "sku_id": "SELLER_C-025",
    "seller_id": "seller_c",
    "seller_name": "Yiwu Brightline Trading",
    "product_line": "Power Bank VoltCell 20000mAh",
    "variant": "Pink",
    "unit_price_usd": 13.39,
    "moq": 200,
    "stock_qty": 560,
    "lead_time_days": 15
  },
  {
    "sku_id": "SELLER_C-026",
    "seller_id": "seller_c",
    "seller_name": "Yiwu Brightline Trading",
    "product_line": "USB-C Cable FlexLink 100W",
    "variant": "1m",
    "unit_price_usd": 2.75,
    "moq": 300,
    "stock_qty": 340,
    "lead_time_days": 10
  },
  {
    "sku_id": "SELLER_C-027",
    "seller_id": "seller_c",
    "seller_name": "Yiwu Brightline Trading",
    "product_line": "USB-C Cable FlexLink 100W",
    "variant": "2m",
    "unit_price_usd": 2.31,
    "moq": 200,
    "stock_qty": 45,
    "lead_time_days": 10
  },
  {
    "sku_id": "SELLER_C-028",
    "seller_id": "seller_c",
    "seller_name": "Yiwu Brightline Trading",
    "product_line": "USB-C Cable FlexLink 100W",
    "variant": "0.5m",
    "unit_price_usd": 2.62,
    "moq": 100,
    "stock_qty": 80,
    "lead_time_days": 7
  },
  {
    "sku_id": "SELLER_C-029",
    "seller_id": "seller_c",
    "seller_name": "Yiwu Brightline Trading",
    "product_line": "USB-C Cable FlexLink 100W",
    "variant": "3m Braided",
    "unit_price_usd": 2.13,
    "moq": 100,
    "stock_qty": 80,
    "lead_time_days": 12
  },
  {
    "sku_id": "SELLER_C-030",
    "seller_id": "seller_c",
    "seller_name": "Yiwu Brightline Trading",
    "product_line": "USB-C Cable FlexLink 100W",
    "variant": "1m Braided",
    "unit_price_usd": 2.38,
    "moq": 200,
    "stock_qty": 45,
    "lead_time_days": 10
  },
  {
    "sku_id": "SELLER_C-031",
    "seller_id": "seller_c",
    "seller_name": "Yiwu Brightline Trading",
    "product_line": "Phone Case ShieldFlex Clear",
    "variant": "iPhone 16",
    "unit_price_usd": 1.86,
    "moq": 100,
    "stock_qty": 45,
    "lead_time_days": 7
  },
  {
    "sku_id": "SELLER_C-032",
    "seller_id": "seller_c",
    "seller_name": "Yiwu Brightline Trading",
    "product_line": "Phone Case ShieldFlex Clear",
    "variant": "iPhone 16 Pro",
    "unit_price_usd": 1.52,
    "moq": 300,
    "stock_qty": 560,
    "lead_time_days": 7
  },
  {
    "sku_id": "SELLER_C-033",
    "seller_id": "seller_c",
    "seller_name": "Yiwu Brightline Trading",
    "product_line": "Phone Case ShieldFlex Clear",
    "variant": "Galaxy S26",
    "unit_price_usd": 2.31,
    "moq": 100,
    "stock_qty": 45,
    "lead_time_days": 12
  },
  {
    "sku_id": "SELLER_C-034",
    "seller_id": "seller_c",
    "seller_name": "Yiwu Brightline Trading",
    "product_line": "Phone Case ShieldFlex Clear",
    "variant": "Galaxy S26+",
    "unit_price_usd": 1.43,
    "moq": 100,
    "stock_qty": 340,
    "lead_time_days": 7
  },
  {
    "sku_id": "SELLER_C-035",
    "seller_id": "seller_c",
    "seller_name": "Yiwu Brightline Trading",
    "product_line": "Phone Case ShieldFlex Clear",
    "variant": "Pixel 10",
    "unit_price_usd": 1.17,
    "moq": 200,
    "stock_qty": 1200,
    "lead_time_days": 7
  },
  {
    "sku_id": "SELLER_C-036",
    "seller_id": "seller_c",
    "seller_name": "Yiwu Brightline Trading",
    "product_line": "Screen Protector GlassGuard 9H",
    "variant": "iPhone 16",
    "unit_price_usd": 1.2,
    "moq": 300,
    "stock_qty": 340,
    "lead_time_days": 15
  },
  {
    "sku_id": "SELLER_C-037",
    "seller_id": "seller_c",
    "seller_name": "Yiwu Brightline Trading",
    "product_line": "Screen Protector GlassGuard 9H",
    "variant": "iPhone 16 Pro",
    "unit_price_usd": 1.24,
    "moq": 100,
    "stock_qty": 340,
    "lead_time_days": 7
  },
  {
    "sku_id": "SELLER_C-038",
    "seller_id": "seller_c",
    "seller_name": "Yiwu Brightline Trading",
    "product_line": "Screen Protector GlassGuard 9H",
    "variant": "Galaxy S26",
    "unit_price_usd": 1.64,
    "moq": 50,
    "stock_qty": 900,
    "lead_time_days": 15
  },
  {
    "sku_id": "SELLER_C-039",
    "seller_id": "seller_c",
    "seller_name": "Yiwu Brightline Trading",
    "product_line": "Screen Protector GlassGuard 9H",
    "variant": "Galaxy S26+",
    "unit_price_usd": 0.96,
    "moq": 300,
    "stock_qty": 80,
    "lead_time_days": 7
  },
  {
    "sku_id": "SELLER_C-040",
    "seller_id": "seller_c",
    "seller_name": "Yiwu Brightline Trading",
    "product_line": "Screen Protector GlassGuard 9H",
    "variant": "Pixel 10",
    "unit_price_usd": 1.3,
    "moq": 50,
    "stock_qty": 80,
    "lead_time_days": 10
  },
  {
    "sku_id": "SELLER_C-041",
    "seller_id": "seller_c",
    "seller_name": "Yiwu Brightline Trading",
    "product_line": "Car Charger DriveVolt 45W Dual-Port",
    "variant": "Black",
    "unit_price_usd": 6.72,
    "moq": 200,
    "stock_qty": 400,
    "lead_time_days": 18
  },
  {
    "sku_id": "SELLER_C-042",
    "seller_id": "seller_c",
    "seller_name": "Yiwu Brightline Trading",
    "product_line": "Car Charger DriveVolt 45W Dual-Port",
    "variant": "Silver",
    "unit_price_usd": 6.06,
    "moq": 100,
    "stock_qty": 400,
    "lead_time_days": 18
  },
  {
    "sku_id": "SELLER_C-043",
    "seller_id": "seller_c",
    "seller_name": "Yiwu Brightline Trading",
    "product_line": "Car Charger DriveVolt 45W Dual-Port",
    "variant": "Red",
    "unit_price_usd": 7.01,
    "moq": 100,
    "stock_qty": 400,
    "lead_time_days": 14
  }
]